initializer_pkg/__init__.py
initializer_pkg/initializer.py
initializer_pkg/utils.py
project_initializer-1.1.0.dist-info/METADATA
project_initializer-1.1.0.dist-info/WHEEL
project_initializer-1.1.0.dist-info/entry_points.txt
project_initializer-1.1.0.dist-info/top_level.txt
project_initializer-1.1.0.dist-info/RECORD
