Metadata-Version: 2.4
Name: project-initializer
Version: 1.1.0
Summary: A project initializer for web development using Django and React
Author-email: Vervloessem Lucas <lucas.vervloessem.atc@gmail.com>
License-Expression: MIT
Classifier: Programming Language :: Python :: 3
Classifier: Operating System :: OS Independent
Requires-Python: >=3.7
Requires-Dist: questionary
Requires-Dist: gitpython
